qtdata/__init__.py
qtdata/__version__.py
qtdata-0.0.1.dist-info/LICENSE
qtdata-0.0.1.dist-info/METADATA
qtdata-0.0.1.dist-info/WHEEL
qtdata-0.0.1.dist-info/top_level.txt
qtdata-0.0.1.dist-info/RECORD
