Metadata-Version: 2.1
Name: qtdata
Version: 0.0.1
Summary: A finance tool to get stock,fund and futures data base on kinds of quant data
Home-page: https://github.com/rchardzhu/qtdata
Author: Richard Zhu
Author-email: rchardzhu@gmail.com
License: MIT
Project-URL: Documentation, https://github.com/rchardzhu/qtdata
Project-URL: Source, https://github.com/rchardzhu/qtdata
Keywords: finance,quant,stock,fund,futures
Platform: any
Classifier: License :: OSI Approved :: MIT License
Classifier: Programming Language :: Python :: 3.6
Classifier: Programming Language :: Python :: 3.7
Classifier: Programming Language :: Python :: 3.8
Classifier: Programming Language :: Python :: 3.9
License-File: LICENSE
Requires-Dist: requests
Requires-Dist: pandas
Requires-Dist: numpy
Requires-Dist: yfinance
